{
  "unversionedId": "get-started/validator-api-quickstart",
  "id": "get-started/validator-api-quickstart",
  "title": "Validator API quickstart",
  "description": "Learn the ins and outs of contributing to the Tableland docs site.",
  "source": "@site/docs/get-started/validator-api-quickstart.md",
  "sourceDirName": "get-started",
  "slug": "/get-started/validator-api-quickstart",
  "permalink": "/get-started/validator-api-quickstart",
  "draft": false,
  "editUrl": "https://github.com/tablelandnetwork/docs/tree/main/docs/get-started/validator-api-quickstart.md",
  "tags": [],
  "version": "current",
  "lastUpdatedBy": "Author",
  "lastUpdatedAt": 1539502055,
  "formattedLastUpdatedAt": "Oct 14, 2018",
  "frontMatter": {
    "title": "Validator API quickstart",
    "description": "Learn the ins and outs of contributing to the Tableland docs site.",
    "synopsis": "The docs site is built using Docusaurus, a static site generator developed by Meta that is specifically designed for documentation. It offers a number of features, including MDX support (embed JSX in markdown) and various content-friendly plugins. Please ensure you follow the guidelines on writing style as well."
  },
  "sidebar": "getStarted",
  "previous": {
    "title": "Smart contract quickstart",
    "permalink": "/get-started/smart-contract-quickstart"
  }
}