{
  "unversionedId": "get-started/chains/polygon",
  "id": "get-started/chains/polygon",
  "title": "Polygon",
  "description": "An overview of using Polygon with Tableland.",
  "source": "@site/docs/get-started/chains/polygon.md",
  "sourceDirName": "get-started/chains",
  "slug": "/get-started/chains/polygon",
  "permalink": "/get-started/chains/polygon",
  "draft": false,
  "editUrl": "https://github.com/tablelandnetwork/docs/tree/main/docs/get-started/chains/polygon.md",
  "tags": [],
  "version": "current",
  "lastUpdatedBy": "Author",
  "lastUpdatedAt": 1539502055,
  "formattedLastUpdatedAt": "Oct 14, 2018",
  "frontMatter": {
    "title": "Polygon",
    "description": "An overview of using Polygon with Tableland.",
    "synopsis": "Polygon is one of the EVM-compatible Layer 2 solutions that Tableland currently supports. Check out the overview of what this network is and relevant information when using it.",
    "keywords": [
      "polygon"
    ]
  },
  "sidebar": "getStarted",
  "previous": {
    "title": "Optimism",
    "permalink": "/get-started/chains/optimism"
  },
  "next": {
    "title": "Local node",
    "permalink": "/get-started/chains/local"
  }
}