{
  "entrypoints": [
    "main"
  ],
  "origins": {
    "1071": [
      1071
    ],
    "1751": [
      532,
      8421,
      9583,
      1751
    ],
    "2366": [
      2366
    ],
    "3209": [
      3209
    ],
    "4204": [
      4204
    ],
    "5525": [
      8443,
      5525
    ],
    "6048": [
      532,
      3089,
      6103,
      8401,
      8610,
      9782,
      6048
    ],
    "8401": [
      532,
      3089,
      6048,
      6103,
      7918,
      8610,
      8945,
      9782,
      8401
    ],
    "8443": [
      5525,
      8443
    ],
    "8945": [
      532,
      7918,
      8401,
      9782,
      8945
    ],
    "9583": [
      532,
      1751,
      8421,
      9514,
      9583
    ],
    "9782": [
      114,
      428,
      532,
      641,
      894,
      1072,
      1250,
      1588,
      1894,
      2168,
      2891,
      3089,
      4641,
      4832,
      5234,
      5846,
      6048,
      6103,
      7918,
      8203,
      8401,
      8610,
      8770,
      8945,
      9782
    ],
    "17896441": [
      532,
      8401,
      8945,
      9782,
      7918
    ],
    "59362658": [
      2267
    ],
    "60526638": [
      9499
    ],
    "63433667": [
      1037
    ],
    "66406991": [
      110
    ],
    "77183501": [
      9782,
      5846
    ],
    "main": [
      532,
      1303,
      179
    ],
    "runtime~main": [
      179,
      532,
      1303
    ],
    "00fb0677": [
      532,
      1516
    ],
    "01a85c17": [
      532,
      4013
    ],
    "031793e1": [
      1633
    ],
    "050beb03": [
      532,
      4877
    ],
    "05581d68": [
      532,
      2919
    ],
    "078cea13": [
      3019
    ],
    "096bfee4": [
      7178
    ],
    "09f13512": [
      4530
    ],
    "0d5423bb": [
      532,
      2174
    ],
    "0f488fb5": [
      3169
    ],
    "16dfd79c": [
      6703
    ],
    "1a4e3797": [
      532,
      7920
    ],
    "1a617fb6": [
      2112
    ],
    "1be78505": [
      532,
      9583,
      4204
    ],
    "1c57136e": [
      9051
    ],
    "2014c5ac": [
      532,
      1754
    ],
    "219fc4d5": [
      2875
    ],
    "21b35f46": [
      5150
    ],
    "23374ca6": [
      532,
      1751,
      9583,
      8421
    ],
    "234f51ff": [
      2896
    ],
    "25fa4fd9": [
      4904
    ],
    "275158dd": [
      8122
    ],
    "2813d6d7": [
      9782,
      1072
    ],
    "2a3310d2": [
      532,
      1402
    ],
    "2d880e3c": [
      532,
      5482
    ],
    "30a24c52": [
      453
    ],
    "30c61050": [
      9782,
      8770
    ],
    "347c9c5e": [
      2855
    ],
    "3720c009": [
      532,
      3751
    ],
    "373d85c2": [
      4328
    ],
    "37d47053": [
      2232
    ],
    "39389f40": [
      1238
    ],
    "3eec509c": [
      3226
    ],
    "4161d9ff": [
      9780
    ],
    "4364586b": [
      7610
    ],
    "4b9d7775": [
      8270
    ],
    "4c9e35b1": [
      9035
    ],
    "4d2a2f08": [
      532,
      5074
    ],
    "4f9f2e10": [
      7031
    ],
    "5007e6b9": [
      9782,
      4832
    ],
    "536d5fd1": [
      8691
    ],
    "5389b6b3": [
      9782,
      1894
    ],
    "54b3092c": [
      9593
    ],
    "55960ee5": [
      4121
    ],
    "57a2e058": [
      9782,
      5234
    ],
    "5f75ad60": [
      6270
    ],
    "60706b0c": [
      2113
    ],
    "608ae6a4": [
      6938
    ],
    "61bcca26": [
      5377
    ],
    "64a0c5dd": [
      3721
    ],
    "6875c492": [
      532,
      6048,
      8401,
      9782,
      7918
    ],
    "6ae15568": [
      5885
    ],
    "6b6ac6d8": [
      532,
      9815
    ],
    "6b83ecb5": [
      9782,
      2168
    ],
    "6b89937f": [
      6456
    ],
    "6fe1ec5a": [
      9782,
      894
    ],
    "700c545b": [
      5072
    ],
    "73664a40": [
      3514
    ],
    "74e3b1dd": [
      9003
    ],
    "7550674c": [
      532,
      7399
    ],
    "75a862b8": [
      7542
    ],
    "7661071f": [
      9642
    ],
    "7d243378": [
      3403
    ],
    "801a323d": [
      7056
    ],
    "814f3328": [
      2535
    ],
    "81a0fad7": [
      1881
    ],
    "866ee375": [
      2215
    ],
    "868462df": [
      9654
    ],
    "86b8ce54": [
      532,
      6626
    ],
    "87121e3a": [
      9782,
      428
    ],
    "8717b14a": [
      948
    ],
    "8747c05a": [
      4354
    ],
    "87f4e41f": [
      8705
    ],
    "8eb19fc1": [
      2994
    ],
    "91be1129": [
      4902
    ],
    "925b3f96": [
      7551
    ],
    "935f2afb": [
      53
    ],
    "958801d2": [
      2931
    ],
    "9b44ba84": [
      5922
    ],
    "9d754648": [
      2962
    ],
    "9de2d97c": [
      6331
    ],
    "9e4087bc": [
      3608
    ],
    "a0d56cee": [
      532,
      9330
    ],
    "a6aa9e1f": [
      532,
      6048,
      8401,
      9782,
      7918
    ],
    "a7023ddc": [
      1713
    ],
    "a705d6c1": [
      532,
      5188
    ],
    "a80da1cf": [
      3205
    ],
    "a8b4d296": [
      422
    ],
    "aabebbbf": [
      8991
    ],
    "aef2f35b": [
      7685
    ],
    "b0552960": [
      9782,
      4641
    ],
    "b2231f78": [
      532,
      9782,
      641
    ],
    "b2b675dd": [
      533
    ],
    "b2f554cd": [
      1477
    ],
    "b6d46b44": [
      906
    ],
    "b7664370": [
      9622
    ],
    "b849206f": [
      9782,
      2891
    ],
    "bbe9041d": [
      532,
      6113
    ],
    "bce04178": [
      532,
      3284
    ],
    "c4cee7a0": [
      8908
    ],
    "c5317379": [
      7315
    ],
    "c60fe4fd": [
      9290
    ],
    "c81f4a78": [
      532,
      9782,
      114
    ],
    "c91b32e5": [
      2466
    ],
    "cca98b34": [
      532,
      943
    ],
    "ccc35202": [
      6402
    ],
    "ccc49370": [
      532,
      6048,
      8401,
      9782,
      7918
    ],
    "ce9ea94e": [
      4910
    ],
    "cfeac875": [
      9782,
      1250
    ],
    "d015beca": [
      532,
      9782,
      1588
    ],
    "d1d86c42": [
      8808
    ],
    "d1e84aab": [
      4914
    ],
    "d30631c5": [
      532,
      8950
    ],
    "d39250ba": [
      532,
      7543
    ],
    "d7af6dc1": [
      9524
    ],
    "d9f32620": [
      1914
    ],
    "dad9be14": [
      7872
    ],
    "df203c0f": [
      9924
    ],
    "dfc4a26d": [
      2263
    ],
    "e16015ca": [
      9700
    ],
    "e23af714": [
      9782,
      8203
    ],
    "e273c56f": [
      2362
    ],
    "e50fcb0b": [
      4172
    ],
    "e7bfe382": [
      4653
    ],
    "eab96010": [
      330
    ],
    "eb9e5c7b": [
      532,
      3755
    ],
    "efc9888f": [
      532,
      8774
    ],
    "f30ccce9": [
      3005
    ],
    "f4894934": [
      532,
      5588
    ],
    "f4f34a3a": [
      8636
    ],
    "f9b4d604": [
      532,
      39
    ],
    "styles": [
      39,
      114,
      179,
      641,
      943,
      1303,
      1402,
      1516,
      1588,
      1751,
      1754,
      2174,
      2919,
      3089,
      3284,
      3751,
      3755,
      4013,
      4877,
      5074,
      5188,
      5482,
      5588,
      6048,
      6103,
      6113,
      6626,
      7399,
      7543,
      7918,
      7920,
      8401,
      8421,
      8610,
      8774,
      8945,
      8950,
      9330,
      9514,
      9583,
      9782,
      9815,
      532
    ]
  },
  "assets": {
    "39": {
      "js": [
        {
          "file": "assets/js/f9b4d604.bff9f827.js",
          "hash": "3f03e7a478d22b18",
          "publicPath": "/assets/js/f9b4d604.bff9f827.js"
        }
      ]
    },
    "53": {
      "js": [
        {
          "file": "assets/js/935f2afb.fefc8466.js",
          "hash": "243c2fec59d6c8b4",
          "publicPath": "/assets/js/935f2afb.fefc8466.js"
        }
      ]
    },
    "110": {
      "js": [
        {
          "file": "assets/js/66406991.11cadb6e.js",
          "hash": "aeee6aa95c1f503c",
          "publicPath": "/assets/js/66406991.11cadb6e.js"
        }
      ]
    },
    "114": {
      "js": [
        {
          "file": "assets/js/c81f4a78.2ca12868.js",
          "hash": "ecb57bfe0d4adc0a",
          "publicPath": "/assets/js/c81f4a78.2ca12868.js"
        }
      ]
    },
    "179": {
      "js": [
        {
          "file": "assets/js/main.de611aaa.js",
          "hash": "e752b215160fa7a0",
          "publicPath": "/assets/js/main.de611aaa.js"
        }
      ]
    },
    "330": {
      "js": [
        {
          "file": "assets/js/eab96010.593065cb.js",
          "hash": "040155b0d8d9c0c0",
          "publicPath": "/assets/js/eab96010.593065cb.js"
        }
      ]
    },
    "422": {
      "js": [
        {
          "file": "assets/js/a8b4d296.bbca71b4.js",
          "hash": "2314740394700992",
          "publicPath": "/assets/js/a8b4d296.bbca71b4.js"
        }
      ]
    },
    "428": {
      "js": [
        {
          "file": "assets/js/87121e3a.4ebd0250.js",
          "hash": "e213f3603874e190",
          "publicPath": "/assets/js/87121e3a.4ebd0250.js"
        }
      ]
    },
    "453": {
      "js": [
        {
          "file": "assets/js/30a24c52.540bc40f.js",
          "hash": "20e6856743466e23",
          "publicPath": "/assets/js/30a24c52.540bc40f.js"
        }
      ]
    },
    "532": {
      "css": [
        {
          "file": "assets/css/styles.b6f8fcb7.css",
          "hash": "6c889e603bfd2a21",
          "publicPath": "/assets/css/styles.b6f8fcb7.css"
        }
      ]
    },
    "533": {
      "js": [
        {
          "file": "assets/js/b2b675dd.a9783255.js",
          "hash": "3b3aea1bcab32b04",
          "publicPath": "/assets/js/b2b675dd.a9783255.js"
        }
      ]
    },
    "641": {
      "js": [
        {
          "file": "assets/js/b2231f78.cd7b7b15.js",
          "hash": "cc247aeb6cf357c5",
          "publicPath": "/assets/js/b2231f78.cd7b7b15.js"
        }
      ]
    },
    "894": {
      "js": [
        {
          "file": "assets/js/6fe1ec5a.4fe6683e.js",
          "hash": "0b26414e25b711fc",
          "publicPath": "/assets/js/6fe1ec5a.4fe6683e.js"
        }
      ]
    },
    "906": {
      "js": [
        {
          "file": "assets/js/b6d46b44.813e2271.js",
          "hash": "5e9ca910ddc1dcc5",
          "publicPath": "/assets/js/b6d46b44.813e2271.js"
        }
      ]
    },
    "943": {
      "js": [
        {
          "file": "assets/js/cca98b34.b453fc3c.js",
          "hash": "e606c62ee1a0e2ac",
          "publicPath": "/assets/js/cca98b34.b453fc3c.js"
        }
      ]
    },
    "948": {
      "js": [
        {
          "file": "assets/js/8717b14a.91b2a19a.js",
          "hash": "a1638f3d523c35ae",
          "publicPath": "/assets/js/8717b14a.91b2a19a.js"
        }
      ]
    },
    "1037": {
      "js": [
        {
          "file": "assets/js/63433667.3a22c899.js",
          "hash": "1f193a93df46e993",
          "publicPath": "/assets/js/63433667.3a22c899.js"
        }
      ]
    },
    "1071": {
      "js": [
        {
          "file": "assets/js/1071.c0606e49.js",
          "hash": "b0deef5cea674691",
          "publicPath": "/assets/js/1071.c0606e49.js"
        }
      ]
    },
    "1072": {
      "js": [
        {
          "file": "assets/js/2813d6d7.382542d4.js",
          "hash": "cff522a5c90bb780",
          "publicPath": "/assets/js/2813d6d7.382542d4.js"
        }
      ]
    },
    "1238": {
      "js": [
        {
          "file": "assets/js/39389f40.c28ae5f8.js",
          "hash": "33f20c1eab84275a",
          "publicPath": "/assets/js/39389f40.c28ae5f8.js"
        }
      ]
    },
    "1250": {
      "js": [
        {
          "file": "assets/js/cfeac875.0a743fde.js",
          "hash": "677de012cfd95c3b",
          "publicPath": "/assets/js/cfeac875.0a743fde.js"
        }
      ]
    },
    "1303": {
      "js": [
        {
          "file": "assets/js/runtime~main.e69bd40b.js",
          "hash": "d12459dffb64a759",
          "publicPath": "/assets/js/runtime~main.e69bd40b.js"
        }
      ]
    },
    "1402": {
      "js": [
        {
          "file": "assets/js/2a3310d2.b744e3b4.js",
          "hash": "7bf975547da5fb51",
          "publicPath": "/assets/js/2a3310d2.b744e3b4.js"
        }
      ]
    },
    "1477": {
      "js": [
        {
          "file": "assets/js/b2f554cd.683d8933.js",
          "hash": "30965988e177f736",
          "publicPath": "/assets/js/b2f554cd.683d8933.js"
        }
      ]
    },
    "1516": {
      "js": [
        {
          "file": "assets/js/00fb0677.c0ed6212.js",
          "hash": "65b420bfacfbf93e",
          "publicPath": "/assets/js/00fb0677.c0ed6212.js"
        }
      ]
    },
    "1588": {
      "js": [
        {
          "file": "assets/js/d015beca.cab5c2df.js",
          "hash": "a2ce25bbf9cfde2f",
          "publicPath": "/assets/js/d015beca.cab5c2df.js"
        }
      ]
    },
    "1633": {
      "js": [
        {
          "file": "assets/js/031793e1.733c4b43.js",
          "hash": "7adfda73ccee2496",
          "publicPath": "/assets/js/031793e1.733c4b43.js"
        }
      ]
    },
    "1713": {
      "js": [
        {
          "file": "assets/js/a7023ddc.edab8d9d.js",
          "hash": "c134ac01db78498b",
          "publicPath": "/assets/js/a7023ddc.edab8d9d.js"
        }
      ]
    },
    "1751": {
      "js": [
        {
          "file": "assets/js/1751.43500e5d.js",
          "hash": "50b6665e41bdbf7b",
          "publicPath": "/assets/js/1751.43500e5d.js"
        }
      ]
    },
    "1754": {
      "js": [
        {
          "file": "assets/js/2014c5ac.bfad9366.js",
          "hash": "b67125d5745c8e19",
          "publicPath": "/assets/js/2014c5ac.bfad9366.js"
        }
      ]
    },
    "1881": {
      "js": [
        {
          "file": "assets/js/81a0fad7.24c783d4.js",
          "hash": "7c61e57e554b7dc6",
          "publicPath": "/assets/js/81a0fad7.24c783d4.js"
        }
      ]
    },
    "1894": {
      "js": [
        {
          "file": "assets/js/5389b6b3.18bc5738.js",
          "hash": "ab82f7c53a8250dd",
          "publicPath": "/assets/js/5389b6b3.18bc5738.js"
        }
      ]
    },
    "1914": {
      "js": [
        {
          "file": "assets/js/d9f32620.3681374a.js",
          "hash": "1721bc4575758297",
          "publicPath": "/assets/js/d9f32620.3681374a.js"
        }
      ]
    },
    "2112": {
      "js": [
        {
          "file": "assets/js/1a617fb6.9818ac5d.js",
          "hash": "add32f16f904770a",
          "publicPath": "/assets/js/1a617fb6.9818ac5d.js"
        }
      ]
    },
    "2113": {
      "js": [
        {
          "file": "assets/js/60706b0c.9d492108.js",
          "hash": "5a8686683c790210",
          "publicPath": "/assets/js/60706b0c.9d492108.js"
        }
      ]
    },
    "2168": {
      "js": [
        {
          "file": "assets/js/6b83ecb5.1de40d2c.js",
          "hash": "c62e23612b67921e",
          "publicPath": "/assets/js/6b83ecb5.1de40d2c.js"
        }
      ]
    },
    "2174": {
      "js": [
        {
          "file": "assets/js/0d5423bb.7b11df73.js",
          "hash": "b80fa7c3d9433505",
          "publicPath": "/assets/js/0d5423bb.7b11df73.js"
        }
      ]
    },
    "2215": {
      "js": [
        {
          "file": "assets/js/866ee375.407b5c4a.js",
          "hash": "f26f5d960ad5ca5c",
          "publicPath": "/assets/js/866ee375.407b5c4a.js"
        }
      ]
    },
    "2232": {
      "js": [
        {
          "file": "assets/js/37d47053.9d68cbe5.js",
          "hash": "0a820525a6c37917",
          "publicPath": "/assets/js/37d47053.9d68cbe5.js"
        }
      ]
    },
    "2263": {
      "js": [
        {
          "file": "assets/js/dfc4a26d.0819dfd3.js",
          "hash": "9496b56f39b42437",
          "publicPath": "/assets/js/dfc4a26d.0819dfd3.js"
        }
      ]
    },
    "2267": {
      "js": [
        {
          "file": "assets/js/59362658.143814b9.js",
          "hash": "83875b8e143453f6",
          "publicPath": "/assets/js/59362658.143814b9.js"
        }
      ]
    },
    "2362": {
      "js": [
        {
          "file": "assets/js/e273c56f.065407bd.js",
          "hash": "c2f8679d6dc7fe3b",
          "publicPath": "/assets/js/e273c56f.065407bd.js"
        }
      ]
    },
    "2366": {
      "js": [
        {
          "file": "assets/js/2366.6be685d8.js",
          "hash": "e9dc23eaa487503c",
          "publicPath": "/assets/js/2366.6be685d8.js"
        }
      ]
    },
    "2466": {
      "js": [
        {
          "file": "assets/js/c91b32e5.63e12813.js",
          "hash": "a2d6d21dd396820c",
          "publicPath": "/assets/js/c91b32e5.63e12813.js"
        }
      ]
    },
    "2535": {
      "js": [
        {
          "file": "assets/js/814f3328.5d0482b2.js",
          "hash": "2c270e05e4110034",
          "publicPath": "/assets/js/814f3328.5d0482b2.js"
        }
      ]
    },
    "2855": {
      "js": [
        {
          "file": "assets/js/347c9c5e.98d53b87.js",
          "hash": "3c857df9fc2e43ab",
          "publicPath": "/assets/js/347c9c5e.98d53b87.js"
        }
      ]
    },
    "2875": {
      "js": [
        {
          "file": "assets/js/219fc4d5.ec31f762.js",
          "hash": "0df60fffdf7be1b9",
          "publicPath": "/assets/js/219fc4d5.ec31f762.js"
        }
      ]
    },
    "2891": {
      "js": [
        {
          "file": "assets/js/b849206f.47dbeefb.js",
          "hash": "e423c7513e0ec978",
          "publicPath": "/assets/js/b849206f.47dbeefb.js"
        }
      ]
    },
    "2896": {
      "js": [
        {
          "file": "assets/js/234f51ff.15a36e79.js",
          "hash": "e59f2e53a8312d01",
          "publicPath": "/assets/js/234f51ff.15a36e79.js"
        }
      ]
    },
    "2919": {
      "js": [
        {
          "file": "assets/js/05581d68.efd2a1bb.js",
          "hash": "232014883057c815",
          "publicPath": "/assets/js/05581d68.efd2a1bb.js"
        }
      ]
    },
    "2931": {
      "js": [
        {
          "file": "assets/js/958801d2.fe0bae47.js",
          "hash": "3f4c14cee2ae37f0",
          "publicPath": "/assets/js/958801d2.fe0bae47.js"
        }
      ]
    },
    "2962": {
      "js": [
        {
          "file": "assets/js/9d754648.512ab8c5.js",
          "hash": "d1e4e6fa180d25ae",
          "publicPath": "/assets/js/9d754648.512ab8c5.js"
        }
      ]
    },
    "2994": {
      "js": [
        {
          "file": "assets/js/8eb19fc1.b0893d5d.js",
          "hash": "0ff85e0932012875",
          "publicPath": "/assets/js/8eb19fc1.b0893d5d.js"
        }
      ]
    },
    "3005": {
      "js": [
        {
          "file": "assets/js/f30ccce9.3895f314.js",
          "hash": "5e71cc24fdb0849f",
          "publicPath": "/assets/js/f30ccce9.3895f314.js"
        }
      ]
    },
    "3019": {
      "js": [
        {
          "file": "assets/js/078cea13.c7a21ab1.js",
          "hash": "3ca22ed9b2e226e6",
          "publicPath": "/assets/js/078cea13.c7a21ab1.js"
        }
      ]
    },
    "3169": {
      "js": [
        {
          "file": "assets/js/0f488fb5.b4e40a37.js",
          "hash": "3e3ffcc9621d0946",
          "publicPath": "/assets/js/0f488fb5.b4e40a37.js"
        }
      ]
    },
    "3205": {
      "js": [
        {
          "file": "assets/js/a80da1cf.dcb2dd7b.js",
          "hash": "9243f4740cfe2650",
          "publicPath": "/assets/js/a80da1cf.dcb2dd7b.js"
        }
      ]
    },
    "3209": {
      "js": [
        {
          "file": "assets/js/3209.56d19575.js",
          "hash": "aceaff41851eb696",
          "publicPath": "/assets/js/3209.56d19575.js"
        }
      ]
    },
    "3226": {
      "js": [
        {
          "file": "assets/js/3eec509c.fc85242d.js",
          "hash": "369a1edccf68bfd5",
          "publicPath": "/assets/js/3eec509c.fc85242d.js"
        }
      ]
    },
    "3284": {
      "js": [
        {
          "file": "assets/js/bce04178.770d40ec.js",
          "hash": "7cff110a626d57a2",
          "publicPath": "/assets/js/bce04178.770d40ec.js"
        }
      ]
    },
    "3403": {
      "js": [
        {
          "file": "assets/js/7d243378.5b1e21cc.js",
          "hash": "1ed6bbf91499e312",
          "publicPath": "/assets/js/7d243378.5b1e21cc.js"
        }
      ]
    },
    "3514": {
      "js": [
        {
          "file": "assets/js/73664a40.0383f6c3.js",
          "hash": "b69cb94527eaf471",
          "publicPath": "/assets/js/73664a40.0383f6c3.js"
        }
      ]
    },
    "3608": {
      "js": [
        {
          "file": "assets/js/9e4087bc.867a0626.js",
          "hash": "b68e9a52fd0aa3da",
          "publicPath": "/assets/js/9e4087bc.867a0626.js"
        }
      ]
    },
    "3721": {
      "js": [
        {
          "file": "assets/js/64a0c5dd.5bbdbcab.js",
          "hash": "037d1791ad5167ab",
          "publicPath": "/assets/js/64a0c5dd.5bbdbcab.js"
        }
      ]
    },
    "3751": {
      "js": [
        {
          "file": "assets/js/3720c009.5eb0a4a2.js",
          "hash": "22ec181ec67eca24",
          "publicPath": "/assets/js/3720c009.5eb0a4a2.js"
        }
      ]
    },
    "3755": {
      "js": [
        {
          "file": "assets/js/eb9e5c7b.64b92667.js",
          "hash": "bdde05951310ee55",
          "publicPath": "/assets/js/eb9e5c7b.64b92667.js"
        }
      ]
    },
    "4013": {
      "js": [
        {
          "file": "assets/js/01a85c17.f6a2948f.js",
          "hash": "54aee5c027fdd131",
          "publicPath": "/assets/js/01a85c17.f6a2948f.js"
        }
      ]
    },
    "4121": {
      "js": [
        {
          "file": "assets/js/55960ee5.52204831.js",
          "hash": "92b405de61ffc1cd",
          "publicPath": "/assets/js/55960ee5.52204831.js"
        }
      ]
    },
    "4172": {
      "js": [
        {
          "file": "assets/js/e50fcb0b.052e9a3a.js",
          "hash": "91c7cf094c7ffc1c",
          "publicPath": "/assets/js/e50fcb0b.052e9a3a.js"
        }
      ]
    },
    "4204": {
      "js": [
        {
          "file": "assets/js/4204.5c832156.js",
          "hash": "99cb14e6d7e42150",
          "publicPath": "/assets/js/4204.5c832156.js"
        },
        {
          "file": "assets/js/1be78505.e2be1628.js",
          "hash": "e07049052c092c39",
          "publicPath": "/assets/js/1be78505.e2be1628.js"
        }
      ]
    },
    "4328": {
      "js": [
        {
          "file": "assets/js/373d85c2.0b61260a.js",
          "hash": "20ed79b0929b9b05",
          "publicPath": "/assets/js/373d85c2.0b61260a.js"
        }
      ]
    },
    "4354": {
      "js": [
        {
          "file": "assets/js/8747c05a.f3abebd0.js",
          "hash": "b52101114881f563",
          "publicPath": "/assets/js/8747c05a.f3abebd0.js"
        }
      ]
    },
    "4530": {
      "js": [
        {
          "file": "assets/js/09f13512.f3aea2c3.js",
          "hash": "3b50d505b74b7252",
          "publicPath": "/assets/js/09f13512.f3aea2c3.js"
        }
      ]
    },
    "4641": {
      "js": [
        {
          "file": "assets/js/b0552960.bbe37bb5.js",
          "hash": "6469b03d68a9f5c1",
          "publicPath": "/assets/js/b0552960.bbe37bb5.js"
        }
      ]
    },
    "4653": {
      "js": [
        {
          "file": "assets/js/e7bfe382.5f64cc50.js",
          "hash": "d7c73a088a8b9271",
          "publicPath": "/assets/js/e7bfe382.5f64cc50.js"
        }
      ]
    },
    "4832": {
      "js": [
        {
          "file": "assets/js/5007e6b9.595f457e.js",
          "hash": "55c383fe53613f29",
          "publicPath": "/assets/js/5007e6b9.595f457e.js"
        }
      ]
    },
    "4877": {
      "js": [
        {
          "file": "assets/js/050beb03.42fdeb02.js",
          "hash": "8835a26250b65295",
          "publicPath": "/assets/js/050beb03.42fdeb02.js"
        }
      ]
    },
    "4902": {
      "js": [
        {
          "file": "assets/js/91be1129.572c1b8f.js",
          "hash": "3499ab7ea741e50a",
          "publicPath": "/assets/js/91be1129.572c1b8f.js"
        }
      ]
    },
    "4904": {
      "js": [
        {
          "file": "assets/js/25fa4fd9.57b06791.js",
          "hash": "5270aa82137c9104",
          "publicPath": "/assets/js/25fa4fd9.57b06791.js"
        }
      ]
    },
    "4910": {
      "js": [
        {
          "file": "assets/js/ce9ea94e.0088287c.js",
          "hash": "15e7f6e3fee1b00e",
          "publicPath": "/assets/js/ce9ea94e.0088287c.js"
        }
      ]
    },
    "4914": {
      "js": [
        {
          "file": "assets/js/d1e84aab.d9d5e663.js",
          "hash": "5571a8150779a375",
          "publicPath": "/assets/js/d1e84aab.d9d5e663.js"
        }
      ]
    },
    "5072": {
      "js": [
        {
          "file": "assets/js/700c545b.605a8aa5.js",
          "hash": "7b96ca2bc96093c0",
          "publicPath": "/assets/js/700c545b.605a8aa5.js"
        }
      ]
    },
    "5074": {
      "js": [
        {
          "file": "assets/js/4d2a2f08.81dd3676.js",
          "hash": "4b67e8279a7e1ebe",
          "publicPath": "/assets/js/4d2a2f08.81dd3676.js"
        }
      ]
    },
    "5150": {
      "js": [
        {
          "file": "assets/js/21b35f46.26216a06.js",
          "hash": "e4adc27b6bf2e17d",
          "publicPath": "/assets/js/21b35f46.26216a06.js"
        }
      ]
    },
    "5188": {
      "js": [
        {
          "file": "assets/js/a705d6c1.4b8c6a16.js",
          "hash": "d8c4f96511d61d18",
          "publicPath": "/assets/js/a705d6c1.4b8c6a16.js"
        }
      ]
    },
    "5234": {
      "js": [
        {
          "file": "assets/js/57a2e058.4ae615df.js",
          "hash": "b473391b1bd9fec5",
          "publicPath": "/assets/js/57a2e058.4ae615df.js"
        }
      ]
    },
    "5377": {
      "js": [
        {
          "file": "assets/js/61bcca26.efb1d1cb.js",
          "hash": "4fb0c8d83fa9962d",
          "publicPath": "/assets/js/61bcca26.efb1d1cb.js"
        }
      ]
    },
    "5482": {
      "js": [
        {
          "file": "assets/js/2d880e3c.a3b71a67.js",
          "hash": "7ad9e9d0fa1c0684",
          "publicPath": "/assets/js/2d880e3c.a3b71a67.js"
        }
      ]
    },
    "5525": {
      "js": [
        {
          "file": "assets/js/5525.640f1c90.js",
          "hash": "fea624235d4bc6e9",
          "publicPath": "/assets/js/5525.640f1c90.js"
        }
      ]
    },
    "5588": {
      "js": [
        {
          "file": "assets/js/f4894934.c73f2032.js",
          "hash": "aadedd9f5d693390",
          "publicPath": "/assets/js/f4894934.c73f2032.js"
        }
      ]
    },
    "5846": {
      "js": [
        {
          "file": "assets/js/77183501.4c6acaa5.js",
          "hash": "8c4013c367ce0f6b",
          "publicPath": "/assets/js/77183501.4c6acaa5.js"
        }
      ]
    },
    "5885": {
      "js": [
        {
          "file": "assets/js/6ae15568.85d7229b.js",
          "hash": "aed1cbee3e4d22a1",
          "publicPath": "/assets/js/6ae15568.85d7229b.js"
        }
      ]
    },
    "5922": {
      "js": [
        {
          "file": "assets/js/9b44ba84.c49f5aba.js",
          "hash": "abb3564a686e1382",
          "publicPath": "/assets/js/9b44ba84.c49f5aba.js"
        }
      ]
    },
    "6048": {
      "js": [
        {
          "file": "assets/js/6048.6bdc25a1.js",
          "hash": "84a56fd64adb413c",
          "publicPath": "/assets/js/6048.6bdc25a1.js"
        }
      ]
    },
    "6113": {
      "js": [
        {
          "file": "assets/js/bbe9041d.1d69b1ee.js",
          "hash": "c99e8cace3d624b7",
          "publicPath": "/assets/js/bbe9041d.1d69b1ee.js"
        }
      ]
    },
    "6270": {
      "js": [
        {
          "file": "assets/js/5f75ad60.5c7d5fc4.js",
          "hash": "a356e83407d03701",
          "publicPath": "/assets/js/5f75ad60.5c7d5fc4.js"
        }
      ]
    },
    "6331": {
      "js": [
        {
          "file": "assets/js/9de2d97c.f2cad068.js",
          "hash": "0a3b9a010ee3b012",
          "publicPath": "/assets/js/9de2d97c.f2cad068.js"
        }
      ]
    },
    "6402": {
      "js": [
        {
          "file": "assets/js/ccc35202.94a8ac59.js",
          "hash": "692feadf2e182ec1",
          "publicPath": "/assets/js/ccc35202.94a8ac59.js"
        }
      ]
    },
    "6456": {
      "js": [
        {
          "file": "assets/js/6b89937f.41f4990e.js",
          "hash": "dda4f7d94d4af739",
          "publicPath": "/assets/js/6b89937f.41f4990e.js"
        }
      ]
    },
    "6626": {
      "js": [
        {
          "file": "assets/js/86b8ce54.ebc29678.js",
          "hash": "27c631195ce1a90f",
          "publicPath": "/assets/js/86b8ce54.ebc29678.js"
        }
      ]
    },
    "6703": {
      "js": [
        {
          "file": "assets/js/16dfd79c.95c662d9.js",
          "hash": "e398d523814f801c",
          "publicPath": "/assets/js/16dfd79c.95c662d9.js"
        }
      ]
    },
    "6938": {
      "js": [
        {
          "file": "assets/js/608ae6a4.ff998e80.js",
          "hash": "53e201ead13dd7da",
          "publicPath": "/assets/js/608ae6a4.ff998e80.js"
        }
      ]
    },
    "7031": {
      "js": [
        {
          "file": "assets/js/4f9f2e10.79917854.js",
          "hash": "80293778fdc3eefc",
          "publicPath": "/assets/js/4f9f2e10.79917854.js"
        }
      ]
    },
    "7056": {
      "js": [
        {
          "file": "assets/js/801a323d.1a8c273a.js",
          "hash": "5f164eedba956919",
          "publicPath": "/assets/js/801a323d.1a8c273a.js"
        }
      ]
    },
    "7178": {
      "js": [
        {
          "file": "assets/js/096bfee4.96051da5.js",
          "hash": "23657af20ab36a7f",
          "publicPath": "/assets/js/096bfee4.96051da5.js"
        }
      ]
    },
    "7315": {
      "js": [
        {
          "file": "assets/js/c5317379.f0841799.js",
          "hash": "2e44b9f4907440ad",
          "publicPath": "/assets/js/c5317379.f0841799.js"
        }
      ]
    },
    "7399": {
      "js": [
        {
          "file": "assets/js/7550674c.036b90ed.js",
          "hash": "f7f6cf826305ffba",
          "publicPath": "/assets/js/7550674c.036b90ed.js"
        }
      ]
    },
    "7542": {
      "js": [
        {
          "file": "assets/js/75a862b8.4521a75d.js",
          "hash": "4e65114a9a16f351",
          "publicPath": "/assets/js/75a862b8.4521a75d.js"
        }
      ]
    },
    "7543": {
      "js": [
        {
          "file": "assets/js/d39250ba.df63dd0c.js",
          "hash": "2ff9ff7f0219b001",
          "publicPath": "/assets/js/d39250ba.df63dd0c.js"
        }
      ]
    },
    "7551": {
      "js": [
        {
          "file": "assets/js/925b3f96.232644d1.js",
          "hash": "e8c2f1b17dccdcb0",
          "publicPath": "/assets/js/925b3f96.232644d1.js"
        }
      ]
    },
    "7610": {
      "js": [
        {
          "file": "assets/js/4364586b.37a6034e.js",
          "hash": "1e43e77fc86309b9",
          "publicPath": "/assets/js/4364586b.37a6034e.js"
        }
      ]
    },
    "7685": {
      "js": [
        {
          "file": "assets/js/aef2f35b.8e9091ad.js",
          "hash": "8bd9b7eec95b76ee",
          "publicPath": "/assets/js/aef2f35b.8e9091ad.js"
        }
      ]
    },
    "7872": {
      "js": [
        {
          "file": "assets/js/dad9be14.57b10fc7.js",
          "hash": "17a57a2a28b7d668",
          "publicPath": "/assets/js/dad9be14.57b10fc7.js"
        }
      ]
    },
    "7918": {
      "js": [
        {
          "file": "assets/js/17896441.c154ed99.js",
          "hash": "8228129a90bbb349",
          "publicPath": "/assets/js/17896441.c154ed99.js"
        },
        {
          "file": "assets/js/6875c492.e0e444d4.js",
          "hash": "d4b257cf13e8a259",
          "publicPath": "/assets/js/6875c492.e0e444d4.js"
        },
        {
          "file": "assets/js/a6aa9e1f.80130601.js",
          "hash": "ea6f61402e003195",
          "publicPath": "/assets/js/a6aa9e1f.80130601.js"
        },
        {
          "file": "assets/js/ccc49370.a83db3bd.js",
          "hash": "e58eee2d16a349ce",
          "publicPath": "/assets/js/ccc49370.a83db3bd.js"
        }
      ]
    },
    "7920": {
      "js": [
        {
          "file": "assets/js/1a4e3797.53a9d3e4.js",
          "hash": "062deb2e602b21e6",
          "publicPath": "/assets/js/1a4e3797.53a9d3e4.js"
        }
      ]
    },
    "8122": {
      "js": [
        {
          "file": "assets/js/275158dd.801a780f.js",
          "hash": "66c54833dc76163b",
          "publicPath": "/assets/js/275158dd.801a780f.js"
        }
      ]
    },
    "8203": {
      "js": [
        {
          "file": "assets/js/e23af714.9a8c144a.js",
          "hash": "263e6b44dcd0cb59",
          "publicPath": "/assets/js/e23af714.9a8c144a.js"
        }
      ]
    },
    "8270": {
      "js": [
        {
          "file": "assets/js/4b9d7775.d7adbea6.js",
          "hash": "db11db36000997db",
          "publicPath": "/assets/js/4b9d7775.d7adbea6.js"
        }
      ]
    },
    "8401": {
      "js": [
        {
          "file": "assets/js/8401.661bc2d3.js",
          "hash": "272ea02dc1237a3c",
          "publicPath": "/assets/js/8401.661bc2d3.js"
        }
      ]
    },
    "8421": {
      "js": [
        {
          "file": "assets/js/23374ca6.139ea350.js",
          "hash": "d1390d0a235b967a",
          "publicPath": "/assets/js/23374ca6.139ea350.js"
        }
      ]
    },
    "8443": {
      "js": [
        {
          "file": "assets/js/8443.eb0070b3.js",
          "hash": "4d6f1abdc1f74787",
          "publicPath": "/assets/js/8443.eb0070b3.js"
        }
      ]
    },
    "8636": {
      "js": [
        {
          "file": "assets/js/f4f34a3a.17f3c600.js",
          "hash": "42e06b9e87a75834",
          "publicPath": "/assets/js/f4f34a3a.17f3c600.js"
        }
      ]
    },
    "8691": {
      "js": [
        {
          "file": "assets/js/536d5fd1.1881050c.js",
          "hash": "320583130ea7edbc",
          "publicPath": "/assets/js/536d5fd1.1881050c.js"
        }
      ]
    },
    "8705": {
      "js": [
        {
          "file": "assets/js/87f4e41f.b7c1470b.js",
          "hash": "06e79365d8375f7e",
          "publicPath": "/assets/js/87f4e41f.b7c1470b.js"
        }
      ]
    },
    "8770": {
      "js": [
        {
          "file": "assets/js/30c61050.068f45d1.js",
          "hash": "4a12f2edbde511f1",
          "publicPath": "/assets/js/30c61050.068f45d1.js"
        }
      ]
    },
    "8774": {
      "js": [
        {
          "file": "assets/js/efc9888f.c9fd8bfe.js",
          "hash": "7ef2ddad3e30475c",
          "publicPath": "/assets/js/efc9888f.c9fd8bfe.js"
        }
      ]
    },
    "8808": {
      "js": [
        {
          "file": "assets/js/d1d86c42.67627554.js",
          "hash": "d582f8a2985bf5c7",
          "publicPath": "/assets/js/d1d86c42.67627554.js"
        }
      ]
    },
    "8908": {
      "js": [
        {
          "file": "assets/js/c4cee7a0.ff4379e2.js",
          "hash": "37a55e12c3c0c13b",
          "publicPath": "/assets/js/c4cee7a0.ff4379e2.js"
        }
      ]
    },
    "8945": {
      "js": [
        {
          "file": "assets/js/8945.23667a59.js",
          "hash": "64d4c9229f4955d8",
          "publicPath": "/assets/js/8945.23667a59.js"
        }
      ]
    },
    "8950": {
      "js": [
        {
          "file": "assets/js/d30631c5.b1585491.js",
          "hash": "acf38a1258b42c00",
          "publicPath": "/assets/js/d30631c5.b1585491.js"
        }
      ]
    },
    "8991": {
      "js": [
        {
          "file": "assets/js/aabebbbf.519f47f6.js",
          "hash": "802b21ade37e031a",
          "publicPath": "/assets/js/aabebbbf.519f47f6.js"
        }
      ]
    },
    "9003": {
      "js": [
        {
          "file": "assets/js/74e3b1dd.4a1bef14.js",
          "hash": "c8faf8f88e86d030",
          "publicPath": "/assets/js/74e3b1dd.4a1bef14.js"
        }
      ]
    },
    "9035": {
      "js": [
        {
          "file": "assets/js/4c9e35b1.bc6c5ade.js",
          "hash": "7f3bb247f1690ffd",
          "publicPath": "/assets/js/4c9e35b1.bc6c5ade.js"
        }
      ]
    },
    "9051": {
      "js": [
        {
          "file": "assets/js/1c57136e.558a206a.js",
          "hash": "3b6c65d9ea9aa964",
          "publicPath": "/assets/js/1c57136e.558a206a.js"
        }
      ]
    },
    "9290": {
      "js": [
        {
          "file": "assets/js/c60fe4fd.4b22f8b3.js",
          "hash": "ba915b10b10ac3f4",
          "publicPath": "/assets/js/c60fe4fd.4b22f8b3.js"
        }
      ]
    },
    "9330": {
      "js": [
        {
          "file": "assets/js/a0d56cee.f7ea3aee.js",
          "hash": "17915439afc7fa1a",
          "publicPath": "/assets/js/a0d56cee.f7ea3aee.js"
        }
      ]
    },
    "9499": {
      "js": [
        {
          "file": "assets/js/60526638.6e933ab3.js",
          "hash": "81160ef0d3a822cd",
          "publicPath": "/assets/js/60526638.6e933ab3.js"
        }
      ]
    },
    "9524": {
      "js": [
        {
          "file": "assets/js/d7af6dc1.c0581b84.js",
          "hash": "58d101ddb6a91d25",
          "publicPath": "/assets/js/d7af6dc1.c0581b84.js"
        }
      ]
    },
    "9583": {
      "js": [
        {
          "file": "assets/js/9583.f59cef62.js",
          "hash": "8dab4f53052b0b99",
          "publicPath": "/assets/js/9583.f59cef62.js"
        }
      ]
    },
    "9593": {
      "js": [
        {
          "file": "assets/js/54b3092c.0aa9848f.js",
          "hash": "68341ae1ff29d5dd",
          "publicPath": "/assets/js/54b3092c.0aa9848f.js"
        }
      ]
    },
    "9622": {
      "js": [
        {
          "file": "assets/js/b7664370.494ec8dc.js",
          "hash": "1b82475c650a5440",
          "publicPath": "/assets/js/b7664370.494ec8dc.js"
        }
      ]
    },
    "9642": {
      "js": [
        {
          "file": "assets/js/7661071f.511aedee.js",
          "hash": "2ebb7f724fa39cfa",
          "publicPath": "/assets/js/7661071f.511aedee.js"
        }
      ]
    },
    "9654": {
      "js": [
        {
          "file": "assets/js/868462df.9cc1fe13.js",
          "hash": "c4f209d04a437865",
          "publicPath": "/assets/js/868462df.9cc1fe13.js"
        }
      ]
    },
    "9700": {
      "js": [
        {
          "file": "assets/js/e16015ca.d1830de3.js",
          "hash": "7f8387c54806de29",
          "publicPath": "/assets/js/e16015ca.d1830de3.js"
        }
      ]
    },
    "9780": {
      "js": [
        {
          "file": "assets/js/4161d9ff.21273cdc.js",
          "hash": "cd0b4987db8d3555",
          "publicPath": "/assets/js/4161d9ff.21273cdc.js"
        }
      ]
    },
    "9782": {
      "js": [
        {
          "file": "assets/js/9782.a8b1b3ae.js",
          "hash": "409c0706b95b6f8e",
          "publicPath": "/assets/js/9782.a8b1b3ae.js"
        }
      ]
    },
    "9815": {
      "js": [
        {
          "file": "assets/js/6b6ac6d8.f663d510.js",
          "hash": "353de925fc69e1ea",
          "publicPath": "/assets/js/6b6ac6d8.f663d510.js"
        }
      ]
    },
    "9924": {
      "js": [
        {
          "file": "assets/js/df203c0f.cba00853.js",
          "hash": "087577b20cd7a766",
          "publicPath": "/assets/js/df203c0f.cba00853.js"
        }
      ]
    }
  }
}